whratio/__about__.py
whratio/__init__.py
whratio/__main__.py
whratio/ratio.py
whratio-3.1.1.dist-info/METADATA
whratio-3.1.1.dist-info/RECORD
whratio-3.1.1.dist-info/WHEEL
whratio-3.1.1.dist-info/entry_points.txt
whratio-3.1.1.dist-info/top_level.txt
