Metadata-Version: 2.1
Name: whratio
Version: 3.1.1
Summary: Calculate integer and decimal aspect ratio for dimensions.
Home-page: https://github.com/mirukan/whratio
Author: miruka
Author-email: miruka@disroot.org
License: LGPLv3
Keywords: calculate aspect ratio dimension width height image video
Platform: UNKNOWN
Classifier: Development Status :: 5 - Production/Stable
Classifier: Intended Audience :: Developers
Classifier: Intended Audience :: End Users/Desktop
Classifier: Environment :: Console
Classifier: Topic :: Utilities
Classifier: License :: OSI Approved :: GNU Lesser General Public License v3 or later (LGPLv3+)
Classifier: Programming Language :: Python :: 3
Classifier: Programming Language :: Python :: 3 :: Only
Classifier: Programming Language :: Python :: 3.5
Classifier: Programming Language :: Python :: 3.6
Classifier: Programming Language :: Python :: 3.7
Classifier: Natural Language :: English
Classifier: Operating System :: POSIX
Requires-Python: >=3.5, <4
